{
  "$schema": "https://biomejs.dev/schemas/1.9.1/schema.json",
  "files": {
    "ignoreUnknown": true
  },
  "vcs": {
    "enabled": true,
    "clientKind": "git",
    "useIgnoreFile": true
  },
  "linter": {
    "enabled": true,
    "rules": {
      "all": true,
      "style": {
        "all": true,
        "noDefaultExport": "off",
        "useFilenamingConvention": {
          "level": "error",
          "options": {
            "strictCase": true,
            "requireAscii": true,
            "filenameCases": ["camelCase", "export"]
          }
        }
      },
      "suspicious": {
        "all": true,
        "noReactSpecificProps": "off"
      }
    }
  },
  "formatter": {
    "enabled": true,
    "formatWithErrors": false,
    "indentStyle": "space",
    "indentWidth": 2,
    "lineWidth": 100,
    "attributePosition": "auto",
    "useEditorconfig": true
  },
  "organizeImports": {
    "enabled": true
  },
  "javascript": {
    "jsxRuntime": "transparent"
  },
  "json": {
    "formatter": {
      "enabled": true
    },
    "linter": {
      "enabled": true
    }
  },
  "css": {
    "formatter": {
      "enabled": true
    },
    "linter": {
      "enabled": true
    }
  }
}
